{
   "_id": "wuIUIyFlx05iZIwR",
   "name": "Determining Ability Scores",
   "permission": {
      "default": 0
   },
   "type": "class",
   "flags": {
      "wc5e": {
         "type": "rule",
         "title": "WC5E.Rules.Mechanics.DeterminingAbilityScores.Label",
         "content": [
            {
               "title": "WC5E.Rules.Mechanics.DeterminingAbilityScores.Description.1.Title",
               "value": "WC5E.Rules.Mechanics.DeterminingAbilityScores.Description.1.Value"
            },
            {
               "value": "WC5E.Rules.Mechanics.DeterminingAbilityScores.Description.2.Value"
            },
            {
               "value": "WC5E.Rules.Mechanics.DeterminingAbilityScores.Description.3.Value"
            },
            {
               "value": "WC5E.Rules.Mechanics.DeterminingAbilityScores.Description.4.Value"
            },
            {
               "title": "WC5E.Rules.Mechanics.DeterminingAbilityScores.Description.5.Title",
               "value": "WC5E.Rules.Mechanics.DeterminingAbilityScores.Description.5.Value"
            }
         ],
         "prev": {
            "pack": "wc5e_rules",
            "node": "TcENfzq00aaPt8Hp",
            "label": "WC5E.Rules.Mechanics.AbilityScoreSummary.Label"
         },
         "next": {
            "pack": "wc5e_rules",
            "node": "8FMb36eUyacdaVnm",
            "label": "WC5E.Rules.Mechanics.Beyond1stLevel.Label"
         }
      }
   },
   "effects": []
}
