{
   "_id": "wl2G6ghGhmHWPhRz",
   "name": "Weapons and Armor",
   "permission": {
      "default": 0
   },
   "type": "class",
   "flags": {
      "wc5e": {
         "type": "rule",
         "title": "WC5E.Rules.Mechanics.WeaponsAndArmor.Label",
         "content": [
            {
               "table": {
                  "head": [
                     {
                        "title": "WC5E.UI.Name"
                     },
                     {
                        "title": "WC5E.UI.Cost",
                        "class": "numberCol"
                     },
                     {
                        "title": "WC5E.UI.Mass",
                        "class": "numberCol"
                     },
                     {
                        "title": "WC5E.UI.Damage",
                        "class": "numberCol"
                     },
                     {
                        "title": "WC5E.UI.Properties"
                     },
                     {
                        "title": "WC5E.UI.Proficiency"
                     }
                  ],
                  "rows": [
                     [
                        {
                           "link": {
                              "pack": "warcraft5e.wc5e_items",
                              "node": "H9mvCWwGzgmMWCVL",
                              "label": "WC5E.Items.AttackClaws.Label"
                           }
                        },
                        {
                           "value": 2,
                           "unit": "WC5E.UI.Units.Gp"
                        },
                        {
                           "value": 2,
                           "unit": "WC5E.UI.Units.Lb"
                        },
                        {
                           "value": "1d4",
                           "text": "WC5E.UI.WeaponProps.Finesse"
                        }
                     ],
                     [
                        {
                           "link": {
                              "pack": "warcraft5e.wc5e_items",
                              "node": "lfZWUXGc3PPojAlI",
                              "label": "WC5E.Items.Bayonet.Label"
                           }
                        },
                        {
                        },
                        {
                        },
                        {
                           "text": "WC5E.Items.Bayonet.Description.1.Value"
                        }
                     ],
                     [
                        {
                           "link": {
                              "pack": "warcraft5e.wc5e_items",
                              "node": "lfZWUXGc3PPojAlI",
                              "label": "WC5E.Items.GarroteWire.Label"
                           }
                        },
                        {
                        },
                        {
                        },
                        {
                           "text": "WC5E.Items.GarroteWire.Description.1.Value"
                        }
                     ]
                  ]
               }
            }
         ],
         "prev": {
            "pack": "wc5e_rules",
            "node": "8a9UvmZT9MkLygR5",
            "label": "WC5E.Rules.Mechanics.Wealth.Label"
         },
         "next": {
            "pack": "wc5e_rules",
            "node": "cq8YZHBjsac3LmSr",
            "label": "WC5E.Rules.Mechanics.WeaponsAndArmor.Label"
         }
      }
   }
}